lumberjack_sdk/__init__.py
lumberjack_sdk/__init__.pyi
lumberjack_sdk/batch.py
lumberjack_sdk/batch.pyi
lumberjack_sdk/code_snippets.py
lumberjack_sdk/code_snippets.pyi
lumberjack_sdk/config.py
lumberjack_sdk/config.pyi
lumberjack_sdk/console_formatter.py
lumberjack_sdk/console_formatter.pyi
lumberjack_sdk/constants.py
lumberjack_sdk/constants.pyi
lumberjack_sdk/core.py
lumberjack_sdk/core.pyi
lumberjack_sdk/exception_handlers.py
lumberjack_sdk/exception_handlers.pyi
lumberjack_sdk/exporters.py
lumberjack_sdk/exporters.pyi
lumberjack_sdk/fallback_exporters.py
lumberjack_sdk/fallback_exporters.pyi
lumberjack_sdk/log.py
lumberjack_sdk/log.pyi
lumberjack_sdk/logging_instrumentation.py
lumberjack_sdk/logging_instrumentation.pyi
lumberjack_sdk/lumberjack_django.py
lumberjack_sdk/lumberjack_django.pyi
lumberjack_sdk/lumberjack_fastapi.py
lumberjack_sdk/lumberjack_fastapi.pyi
lumberjack_sdk/lumberjack_flask.py
lumberjack_sdk/lumberjack_flask.pyi
lumberjack_sdk/lumberjack_trace.py
lumberjack_sdk/lumberjack_trace.pyi
lumberjack_sdk/metrics.py
lumberjack_sdk/metrics.pyi
lumberjack_sdk/metrics_exporter.py
lumberjack_sdk/metrics_exporter.pyi
lumberjack_sdk/object_exporter.py
lumberjack_sdk/object_exporter.pyi
lumberjack_sdk/object_registration.py
lumberjack_sdk/object_registration.pyi
lumberjack_sdk/py.typed
lumberjack_sdk/span.py
lumberjack_sdk/span.pyi
lumberjack_sdk/stdout_override.py
lumberjack_sdk/stdout_override.pyi
lumberjack_sdk/trace_helpers.py
lumberjack_sdk/trace_helpers.pyi
lumberjack_sdk/traceparent_api.py
lumberjack_sdk/traceparent_api.pyi
lumberjack_sdk/internal_utils/core_interface.py
lumberjack_sdk/internal_utils/fallback_logger.py
lumberjack_sdk/internal_utils/flush_timer.py
lumberjack_sdk/local_server/INSTALL_INSTRUCTIONS.md
lumberjack_sdk/local_server/__init__.py
lumberjack_sdk/local_server/__init__.pyi
lumberjack_sdk/local_server/cli.py
lumberjack_sdk/local_server/cli.pyi
lumberjack_sdk/local_server/database.py
lumberjack_sdk/local_server/database.pyi
lumberjack_sdk-2.0.9.dist-info/METADATA
lumberjack_sdk-2.0.9.dist-info/WHEEL
lumberjack_sdk-2.0.9.dist-info/entry_points.txt
lumberjack_sdk-2.0.9.dist-info/licenses/LICENSE
lumberjack_sdk-2.0.9.dist-info/RECORD
