Metadata-Version: 2.4
Name: lumberjack_sdk
Version: 2.0.9
Summary: The Lumberjack Python SDK
Project-URL: Homepage, https://github.com/treebeardhq/lumberjack-sdk-python
Project-URL: Bug Tracker, https://github.com/treebeardhq/lumberjack-sdk-python/issues
Author-email: George Mayer <george@treebeardhq.com>
License-File: LICENSE
Classifier: License :: OSI Approved :: MIT License
Classifier: Operating System :: OS Independent
Classifier: Programming Language :: Python :: 3
Requires-Python: >=3.10
Requires-Dist: opentelemetry-instrumentation-logging>=0.48b0
Requires-Dist: opentelemetry-sdk>=1.27.0
Requires-Dist: opentelemetry-semantic-conventions>=0.48b0
Requires-Dist: termcolor>=2.0.0
Provides-Extra: dev
Requires-Dist: black>=23.0.0; extra == 'dev'
Requires-Dist: build>=1.2.2; extra == 'dev'
Requires-Dist: fastapi>=0.100.0; extra == 'dev'
Requires-Dist: freezegun>=1.5.2; extra == 'dev'
Requires-Dist: grpcio-tools>=1.60.0; extra == 'dev'
Requires-Dist: grpcio>=1.60.0; extra == 'dev'
Requires-Dist: mcp>=1.0.0; extra == 'dev'
Requires-Dist: mypy>=1.0.0; extra == 'dev'
Requires-Dist: opentelemetry-exporter-otlp-proto-grpc>=1.27.0; extra == 'dev'
Requires-Dist: opentelemetry-exporter-otlp-proto-http>=1.36.0; extra == 'dev'
Requires-Dist: opentelemetry-instrumentation-django>=0.48b0; extra == 'dev'
Requires-Dist: opentelemetry-instrumentation-fastapi>=0.45b0; extra == 'dev'
Requires-Dist: opentelemetry-instrumentation-flask>=0.48b0; extra == 'dev'
Requires-Dist: opentelemetry-proto>=1.27.0; extra == 'dev'
Requires-Dist: packaging>=21.0; extra == 'dev'
Requires-Dist: psutil>=7.0.0; extra == 'dev'
Requires-Dist: pytest-cov>=4.0.0; extra == 'dev'
Requires-Dist: pytest>=7.0.0; extra == 'dev'
Requires-Dist: requests>=2.28.0; extra == 'dev'
Requires-Dist: ruff>=0.0.290; extra == 'dev'
Requires-Dist: types-requests>=2.32.0; extra == 'dev'
Requires-Dist: uvicorn>=0.25.0; extra == 'dev'
Requires-Dist: websockets>=12.0; extra == 'dev'
Provides-Extra: django
Requires-Dist: opentelemetry-instrumentation-django>=0.48b0; extra == 'django'
Provides-Extra: fastapi
Requires-Dist: opentelemetry-instrumentation-fastapi>=0.45b0; extra == 'fastapi'
Provides-Extra: flask
Requires-Dist: opentelemetry-instrumentation-flask>=0.48b0; extra == 'flask'
Provides-Extra: local-server
Requires-Dist: fastapi>=0.100.0; extra == 'local-server'
Requires-Dist: grpcio-tools>=1.60.0; extra == 'local-server'
Requires-Dist: grpcio>=1.60.0; extra == 'local-server'
Requires-Dist: mcp>=1.0.0; extra == 'local-server'
Requires-Dist: opentelemetry-exporter-otlp-proto-grpc>=1.27.0; extra == 'local-server'
Requires-Dist: opentelemetry-exporter-otlp-proto-http>=1.36.0; extra == 'local-server'
Requires-Dist: opentelemetry-proto>=1.27.0; extra == 'local-server'
Requires-Dist: packaging>=21.0; extra == 'local-server'
Requires-Dist: psutil>=7.0.0; extra == 'local-server'
Requires-Dist: requests>=2.28.0; extra == 'local-server'
Requires-Dist: uvicorn>=0.25.0; extra == 'local-server'
Requires-Dist: websockets>=12.0; extra == 'local-server'
Provides-Extra: test
Requires-Dist: pytest-cov>=4.0.0; extra == 'test'
Requires-Dist: pytest-mock>=3.0.0; extra == 'test'
Requires-Dist: pytest>=7.0.0; extra == 'test'
Provides-Extra: web
Requires-Dist: opentelemetry-instrumentation-django>=0.48b0; extra == 'web'
Requires-Dist: opentelemetry-instrumentation-fastapi>=0.45b0; extra == 'web'
Requires-Dist: opentelemetry-instrumentation-flask>=0.48b0; extra == 'web'
